AskCheckSum.cp311-win_amd64.pyd
askchecksum-1.0.1.dist-info/METADATA
askchecksum-1.0.1.dist-info/WHEEL
askchecksum-1.0.1.dist-info/top_level.txt
askchecksum-1.0.1.dist-info/RECORD
