Metadata-Version: 2.4
Name: AskCheckSum
Version: 1.0.1
Summary: AskCheckSum
Author: hackzy
Author-email: hufazyj@gmail.com
Dynamic: author
Dynamic: author-email
Dynamic: summary
